distribute_setup.py
setup.py
Python_ETL.egg-info/PKG-INFO
Python_ETL.egg-info/SOURCES.txt
Python_ETL.egg-info/dependency_links.txt
Python_ETL.egg-info/requires.txt
Python_ETL.egg-info/top_level.txt
cardsharp/__init__.py
cardsharp/common_tasks.py
cardsharp/configuration.py
cardsharp/convert.py
cardsharp/csharp.config
cardsharp/data.py
cardsharp/errors.py
cardsharp/flags.py
cardsharp/format.py
cardsharp/merge.py
cardsharp/rows.py
cardsharp/rules.py
cardsharp/tasks.py
cardsharp/test.py
cardsharp/util.py
cardsharp/variables.py
cardsharp/docs/source/conf.py
cardsharp/docs/source/index.rst
cardsharp/docs/source/_static/default.css_t
cardsharp/docs/source/loaders/__init__.rst
cardsharp/docs/source/loaders/csharp.rst
cardsharp/docs/source/loaders/excel.rst
cardsharp/docs/source/loaders/options.rst
cardsharp/docs/source/loaders/text.rst
cardsharp/docs/source/loaders/csharp/__init__.rst
cardsharp/docs/source/loaders/csharp/codec.rst
cardsharp/docs/source/loaders/csharp/csharp.rst
cardsharp/docs/source/loaders/csharp/sevenzip.rst
cardsharp/docs/source/modules/__init__.rst
cardsharp/docs/source/modules/config.rst
cardsharp/docs/source/modules/convert.rst
cardsharp/docs/source/modules/data.rst
cardsharp/docs/source/modules/errors.rst
cardsharp/docs/source/modules/format.rst
cardsharp/docs/source/modules/pavement.rst
cardsharp/docs/source/modules/rows.rst
cardsharp/docs/source/modules/tasks.rst
cardsharp/docs/source/modules/util.rst
cardsharp/docs/source/modules/variables.rst
cardsharp/docs/source/test/__init__.rst
cardsharp/docs/source/test/test_formats.rst
cardsharp/docs/source/test/test_load.rst
cardsharp/docs/source/test/test_variables.rst
cardsharp/docs/source/tutorial/tutorial.rst
cardsharp/drivers/__init__.py
cardsharp/drivers/arff.py
cardsharp/drivers/csv.py
cardsharp/drivers/excel.py
cardsharp/drivers/filter.py
cardsharp/drivers/mongo.py
cardsharp/drivers/mysql.py
cardsharp/drivers/options.py
cardsharp/drivers/sas.py
cardsharp/drivers/text.py
cardsharp/drivers/csharp/__init__.py
cardsharp/drivers/csharp/codec.py
cardsharp/drivers/csharp/csharp.py
cardsharp/drivers/csharp/sevenzip.py
cardsharp/drivers/spss/MIT_spss_code.py
