Metadata-Version: 1.0
Name: Python-ETL
Version: 1.0
Summary: Python-ETL is an open-source Extract, Transform, load (ETL) library written in Python. It allows data to be read from a variety of formats and sources, where it can be cleaned, merged, and transformed using any Python library and then finally saved into all formats python-ETL supports. Ported from cardsharp by Chris Bergstresser.
Home-page: http://python-etl.norc.org
Author: Original: Chris Bergstresser, Current: Michael Jugovich
Author-email: jugovich-michael@norc.org
License: MIT
Keywords: python-etl,excel,spss,sas,extract,transform,load,text,mysql,mssql,
Platform: UNKNOWN
